{
  "main": {
    "am": {
      "dates": {
        "calendars": {
          "gregorian": {
            "months": {
              "format": {
                "abbreviated": {
                  "1": "ጃንዩ",
                  "2": "ፌብሩ",
                  "3": "ማርች",
                  "4": "ኤፕሪ",
                  "5": "ሜይ",
                  "6": "ጁን",
                  "7": "ጁላይ",
                  "8": "ኦገስ",
                  "9": "ሴፕቴ",
                  "10": "ኦክቶ",
                  "11": "ኖቬም",
                  "12": "ዲሴም"
                },
                "narrow": {
                  "1": "ጃ",
                  "2": "ፌ",
                  "3": "ማ",
                  "4": "ኤ",
                  "5": "ሜ",
                  "6": "ጁ",
                  "7": "ጁ",
                  "8": "ኦ",
                  "9": "ሴ",
                  "10": "ኦ",
                  "11": "ኖ",
                  "12": "ዲ"
                },
                "wide": {
                  "1": "ጃንዩወሪ",
                  "2": "ፌብሩወሪ",
                  "3": "ማርች",
                  "4": "ኤፕሪል",
                  "5": "ሜይ",
                  "6": "ጁን",
                  "7": "ጁላይ",
                  "8": "ኦገስት",
                  "9": "ሴፕቴምበር",
                  "10": "ኦክቶበር",
                  "11": "ኖቬምበር",
                  "12": "ዲሴምበር"
                }
              },
              "stand-alone": {
                "abbreviated": {
                  "1": "ጃንዩ",
                  "2": "ፌብሩ",
                  "3": "ማርች",
                  "4": "ኤፕሪ",
                  "5": "ሜይ",
                  "6": "ጁን",
                  "7": "ጁላይ",
                  "8": "ኦገስ",
                  "9": "ሴፕቴ",
                  "10": "ኦክቶ",
                  "11": "ኖቬም",
                  "12": "ዲሴም"
                },
                "narrow": {
                  "1": "ጃ",
                  "2": "ፌ",
                  "3": "ማ",
                  "4": "ኤ",
                  "5": "ሜ",
                  "6": "ጁ",
                  "7": "ጁ",
                  "8": "ኦ",
                  "9": "ሴ",
                  "10": "ኦ",
                  "11": "ኖ",
                  "12": "ዲ"
                },
                "wide": {
                  "1": "ጃንዩወሪ",
                  "2": "ፌብሩወሪ",
                  "3": "ማርች",
                  "4": "ኤፕሪል",
                  "5": "ሜይ",
                  "6": "ጁን",
                  "7": "ጁላይ",
                  "8": "ኦገስት",
                  "9": "ሴፕቴምበር",
                  "10": "ኦክቶበር",
                  "11": "ኖቬምበር",
                  "12": "ዲሴምበር"
                }
              }
            },
            "days": {
              "format": {
                "abbreviated": {
                  "sun": "እሑድ",
                  "mon": "ሰኞ",
                  "tue": "ማክሰ",
                  "wed": "ረቡዕ",
                  "thu": "ሐሙስ",
                  "fri": "ዓርብ",
                  "sat": "ቅዳሜ"
                },
                "narrow": {
                  "sun": "እ",
                  "mon": "ሰ",
                  "tue": "ማ",
                  "wed": "ረ",
                  "thu": "ሐ",
                  "fri": "ዓ",
                  "sat": "ቅ"
                },
                "short": {
                  "sun": "እ",
                  "mon": "ሰ",
                  "tue": "ማ",
                  "wed": "ረ",
                  "thu": "ሐ",
                  "fri": "ዓ",
                  "sat": "ቅ"
                },
                "wide": {
                  "sun": "እሑድ",
                  "mon": "ሰኞ",
                  "tue": "ማክሰኞ",
                  "wed": "ረቡዕ",
                  "thu": "ሐሙስ",
                  "fri": "ዓርብ",
                  "sat": "ቅዳሜ"
                }
              },
              "stand-alone": {
                "abbreviated": {
                  "sun": "እሑድ",
                  "mon": "ሰኞ",
                  "tue": "ማክሰ",
                  "wed": "ረቡዕ",
                  "thu": "ሐሙስ",
                  "fri": "ዓርብ",
                  "sat": "ቅዳሜ"
                },
                "narrow": {
                  "sun": "እ",
                  "mon": "ሰ",
                  "tue": "ማ",
                  "wed": "ረ",
                  "thu": "ሐ",
                  "fri": "ዓ",
                  "sat": "ቅ"
                },
                "short": {
                  "sun": "እ",
                  "mon": "ሰ",
                  "tue": "ማ",
                  "wed": "ረ",
                  "thu": "ሐ",
                  "fri": "ዓ",
                  "sat": "ቅ"
                },
                "wide": {
                  "sun": "እሑድ",
                  "mon": "ሰኞ",
                  "tue": "ማክሰኞ",
                  "wed": "ረቡዕ",
                  "thu": "ሐሙስ",
                  "fri": "ዓርብ",
                  "sat": "ቅዳሜ"
                }
              }
            },
            "dayPeriods": {
              "format": {
                "abbreviated": {
                  "am": "ጥዋት",
                  "pm": "ከሰዓት"
                },
                "narrow": {
                  "am": "ጠ",
                  "pm": "ከ"
                },
                "wide": {
                  "am": "ጥዋት",
                  "pm": "ከሰዓት"
                }
              },
              "stand-alone": {
                "abbreviated": {
                  "am": "ጥዋት",
                  "pm": "ከሰዓት"
                },
                "narrow": {
                  "am": "ጠ",
                  "pm": "ከ"
                },
                "wide": {
                  "am": "ጥዋት",
                  "pm": "ከሰዓት"
                }
              }
            },
            "eras": {
              "eraNames": {
                "0": "ዓመተ ዓለም",
                "1": "ዓመተ ምሕረት"
              },
              "eraAbbr": {
                "0": "ዓ/ዓ",
                "1": "ዓ/ም"
              },
              "eraNarrow": {
                "0": "ዓ/ዓ",
                "1": "ዓ/ም"
              }
            },
            "dateTimeFormats": {
              "full": "{1} {0}",
              "availableFormats": {
                "E": "ccc",
                "EHm": "E HH:mm",
                "EHms": "E HH:mm:ss",
                "Ed": "E d",
                "Ehm": "E h:mm a",
                "Ehms": "E h:mm:ss a",
                "Gy": "y G",
                "GyMMM": "MMM y G",
                "GyMMMEd": "E፣ MMM d፣ y G",
                "GyMMMd": "MMM d፣ y G",
                "H": "H",
                "Hm": "HH:mm",
                "Hms": "HH:mm:ss",
                "M": "L",
                "MEd": "E, M/d",
                "MMM": "LLL",
                "MMMEd": "E, MMM d",
                "MMMMEd": "E, MMMM d",
                "MMMMd": "MMMM d",
                "MMMd": "MMM d",
                "Md": "M/d",
                "d": "d",
                "h": "h a",
                "hm": "h:mm a",
                "hms": "h:mm:ss a",
                "ms": "mm:ss",
                "y": "y",
                "yM": "M/y",
                "yMEd": "E፣ d/M/y",
                "yMMM": "MMM y",
                "yMMMEd": "E፣ MMM d y",
                "yMMMM": "MMMM y",
                "yMMMd": "d MMM y",
                "yMd": "d/M/y",
                "yQQQ": "QQQ y",
                "yQQQQ": "QQQQ y"
              }
            }
          }
        }
      }
    }
  }
}
